[
  {
    "id": "recgFInDYWd6f5Vp1",
    "fields": {
      "Name": "Tech Innovators Inc.",
      "Domain": "https://techinnovatorsbd65.com/",
      "Industry": "Technology",
      "TG Customer?": true,
      "Last Signal Date": "2025-07-20",
      "Contacts": [
        "recXZ80ZKj7YhDGBy",
        "rec1YacV4dTjkuJ60"
      ],
      "Total Contacts": 2,
      "Recent Signal Type": [
        "News",
        "LinkedIn Post"
      ],
      "Signals": [
        "recAvC0sTmm7XCzYO",
        "rec1s0nDG1hdZN6NK"
      ],
      "Industry Insights": {
        "state": "empty",
        "value": null,
        "isStale": true
      },
      "Tasks": [
        "recKgK4S6UvO7QHVK",
        "recMmylIZPReDhAlv"
      ]
    },
    "createdTime": "2025-07-23T14:52:16.000Z"
  },
  {
    "id": "reczb4WnWdfBQXbxL",
    "fields": {
      "Name": "Green Finance Group",
      "Domain": "https://greenfinancegroupf3fe.com/",
      "Industry": "Finance",
      "TG Customer?": true,
      "Last Signal Date": "2025-07-15",
      "Contacts": [
        "recGgLMIukRLyllYS",
        "recm5jMkLrltfy8bm"
      ],
      "Total Contacts": 2,
      "Recent Signal Type": [
        "LinkedIn Post"
      ],
      "Signals": [
        "rec6H7JGl7x5v4PK5"
      ],
      "Industry Insights": {
        "state": "empty",
        "value": null,
        "isStale": true
      },
      "Tasks": [
        "rec4WWI1EVE45iSJ1",
        "recd3j7CBVitLmSV0"
      ]
    },
    "createdTime": "2025-07-23T14:52:16.000Z"
  },
  {
    "id": "rec8807zYZOvLc7Jf",
    "fields": {
      "Name": "HealthFirst Solutions",
      "Domain": "https://healthfirstsolutions5f57.com/",
      "Industry": "Healthcare",
      "TG Customer?": true,
      "Last Signal Date": "2025-07-22",
      "Contacts": [
        "recZROzFsR24ag8QU"
      ],
      "Total Contacts": 1,
      "Recent Signal Type": [
        "Funding"
      ],
      "Signals": [
        "rec2QNWOkebJfbyKS"
      ],
      "Industry Insights": {
        "state": "empty",
        "value": null,
        "isStale": true
      },
      "Tasks": [
        "recPgRj87ZlswSIEM"
      ]
    },
    "createdTime": "2025-07-23T14:52:16.000Z"
  },
  {
    "id": "rec0ZwtZKDoWEEHrh",
    "fields": {
      "Name": "TalentGuard",
      "Domain": "talentguard.com",
      "Industry": "Technology",
      "Last Signal Date": "2025-07-10",
      "Contacts": [
        "recn78Wyev5mpqQZi"
      ],
      "Total Contacts": 1,
      "Recent Signal Type": [
        "Other"
      ],
      "Signals": [
        "recTgXhhnsM8ZnbfK"
      ],
      "Industry Insights": {
        "state": "empty",
        "value": null,
        "isStale": true
      },
      "Tasks": [
        "recC3wCt9ZKjXtPqG"
      ]
    },
    "createdTime": "2025-07-23T14:52:16.000Z"
  },
  {
    "id": "recPeemRANU5yvpvD",
    "fields": {
      "Name": "EthosEnergyttt",
      "Domain": "https://ethosenergy.com/",
      "Industry": "Energy",
      "TG Customer?": true,
      "Last Signal Date": "2025-06-19",
      "Total Contacts": 0,
      "Industry Insights": {
        "state": "empty",
        "value": null,
        "isStale": true
      },
      "Opportunities": [
        "reciBQHkJ084mzqp6",
        "rec7UeskPHpBJuHil",
        "rec0mzS4pQkXTSEIE",
        "rec25hTy7bTVonUWL"
      ],
      "Company Insights": [
        "recgw42JY1jV3Aa9B",
        "recsLKEdYmSwtzZDc",
        "recMfT5XFZ258bUCf",
        "recr3CmlJH8ti41sK",
        "recSa1IWR3aHmrsFl"
      ],
      "Direct Quotes (from Company Insights)": [
        "“Our reputation isn’t great… we can’t answer an executive leader’s response.” – Hazel Smith, May 1 2025",
        "“I need to see who’s entered goals by function and country.” – Hazel Smith, May 1 & 8 2025",
        "“We should be having a monthly customer check-in… pull our service level agreement and take a look at that.” – Hazel Smith, May 1 2025",
        "“We splice TalentGuard with HRIS data using VLOOKUP to spot terminated employees and compliance gaps.” – Blaine Boxwell, May 8 2025",
        "“We splice TalentGuard with HRIS data using VLOOKUP to spot terminated employees and compliance gaps.” – Blaine Boxwell, May 8 2025"
      ],
      "Description (from Company Insights)": [
        "Reporting bug in goal dashboards damaged HR reputation and blocked executive answers.",
        "Need function- and country-level goal-completion breakdowns to guide follow-ups and cultural compliance.",
        "HR ready for formal monthly SLA reviews with vendor to align usage and business outcomes.",
        "Manual Excel filtering (active, start dates, teams) shows appetite for integrated, dynamic reporting.",
        "Manual Excel filtering (active, start dates, teams) shows appetite for integrated, dynamic reporting."
      ]
    },
    "createdTime": "2025-07-25T22:32:05.000Z"
  },
  {
    "id": "recC4vJfPsbVO6qSh",
    "fields": {
      "Name": "EthosEnergy",
      "Domain": "https://ethosenergy.com",
      "Industry": "Energy",
      "Current News": "EthosEnergy has experienced significant corporate developments in 2024-2025. Most notably, One Equity Partners acquired the company for $138 million in January 2025, completing the transaction on December 31, 2024. Previously, EthosEnergy was jointly owned by Wood PLC (51%) and Siemens Energy AG (49%). This acquisition represents a major ownership change and potential growth capital injection.\n\nRecent business expansion includes the May 2025 acquisition of New York-based Turbine Services, Ltd., a specialized manufacturer of aftermarket parts for heavy-duty gas and steam turbines. The company has also secured several major contracts: a multi-year O&M agreement with Rhode Island State Energy Center (July 2025), an O&M contract for Manzanillo Power Land Project (May 2025), and a milestone O&M contract with Raban Al Safina Group in Iraq (May 2025).\n\nEthosEnergy has formed strategic partnerships, including a 2024 joint venture with RAS Group in Iraq for gas turbine component repair facilities, and a partnership with EagleBurgmann for enhanced compressor solutions (December 2024). The company is actively expanding in the Middle East with operations in Iraq and UAE, strengthening its Asia-Pacific presence in Malaysia and Thailand, and maintaining European operations.\n\nUnder CEO Ana Amicarella's leadership, the company is focusing heavily on energy transition solutions including hydrogen-ready technologies, geothermal power expansion, nuclear power services, waste-to-energy solutions, and remote operations digitalization. The company employs approximately 3,600 people globally and is positioning itself as a leading independent service provider for rotating equipment in the energy sector.",
      "Contacts": [
        "recVFYNVCnRIEHbxL",
        "recd4zm3DpQUJSOPy"
      ],
      "Total Contacts": 2,
      "Industry Insights": {
        "state": "empty",
        "value": null,
        "isStale": true
      },
      "Research": [
        "reci5CzMqkJyN0Ycl",
        "rece0S66ilaAddpcr",
        "recw5s5t1BlFjHK10"
      ]
    },
    "createdTime": "2025-07-28T11:19:45.000Z"
  },
  {
    "id": "rec9VRe71REm6Kd68",
    "fields": {
      "Name": "Vonachen",
      "Domain": "https://vonachengroup.com",
      "Industry": "Facilities Services",
      "Current News": "**Recent Developments & News (2025):**\n\n1. **Major Acquisition**: Vonachen Group recently acquired Hasgoe Commercial Cleaning, expanding their service reach into Indiana and Kentucky markets. This strategic acquisition demonstrates their aggressive growth strategy and market expansion focus.\n\n2. **Contract Changes**: In July 2025, the company filed a layoff notice for 184 employees at the Pontiac Caterpillar plant due to losing a temporary staffing contract, showing they also provide temporary staffing services beyond cleaning.\n\n3. **Leadership Recognition**: CEO Matt Vonachen served as ISSA (International Sanitary Supply Association) President in 2023, positioning the company as an industry leader.\n\n**Company Overview:**\nVonachen Group is a fourth-generation, family-owned facility maintenance leader founded in 1968. Based in Peoria, Illinois, they've grown to become one of the largest privately-owned janitorial service companies in the US with 1,001-5,000 employees and approximately $26.7M in revenue.\n\n**Key Services:**\n- Commercial cleaning services\n- Healthcare facility services (hospitals, medical facilities)\n- Industrial cleaning and maintenance\n- Temporary staffing services\n- Facility management solutions\n\n**Buying Committee & Key Decision Makers:**\n\n**Executive Leadership:**\n- **Matt Vonachen** - CEO (4th generation leader, former ISSA President)\n- **Robert Ferlmann, CPA** - Chief Financial Officer\n- **Alex Crowley** - Chief People Officer\n- **Michael DiSparano** - Chief Operating Officer (former role, now at HHS LLC)\n\n**Department Leaders:**\n- **Sean Litvak, CBSE** - Senior Vice President/Southern Region VP of Business Development\n- **Mason Ledgess, CBSE** - Director of Operations\n- **Jeff Durand** - Director of Information Technology\n- **Heather Acerra** - Director of Human Resources\n- **John Austin** - President (regional operations)\n- **Marci Woods** - Controller\n\n**Business Signals & Opportunities:**\n1. **Expansion Focus**: Active acquisition strategy (recent Hasgoe acquisition)\n2. **Technology Investment**: Modernizing facility management solutions\n3. **Healthcare Specialization**: Strong focus on healthcare facility services\n4. **Sustainability Initiatives**: Emphasis on green cleaning solutions\n5. **Employee Development**: Strong internal promotion culture\n6. **Multi-State Operations**: Presence in IL, IN, KY, WI, IA, MS, AL, and expanding\n\n**Target Engagement Opportunities:**\n- Facility management technology solutions\n- Healthcare-specific cleaning innovations\n- Employee training and development programs\n- Sustainability and compliance solutions\n- Quality control and monitoring systems\n- Acquisition integration support services\n\n**Contact Information:**\n- Headquarters: 8900 N Pioneer Rd, Peoria, IL 61615\n- Phone: (309) 691-6202\n- LinkedIn: https://www.linkedin.com/company/vonachen-services-inc-\n\nThis family-owned business values relationships, quality service, and employee development, making them an ideal target for solutions that enhance operational efficiency, support their growth strategy, or improve their service delivery capabilities.",
      "Contacts": [
        "recK7Mu0jBjFBaz1S"
      ],
      "Total Contacts": 1,
      "Industry Insights": {
        "state": "empty",
        "value": null,
        "isStale": true
      },
      "Research": [
        "recdip9JIX6cEvY2P"
      ]
    },
    "createdTime": "2025-07-28T14:15:49.000Z"
  },
  {
    "id": "rec8pEFOXlkoKDAya",
    "fields": {
      "Name": "Vonachen Group",
      "Domain": "https://vonachengroup.com",
      "Industry": "Commercial Cleaning & Facility Maintenance",
      "Current News": "**COMPREHENSIVE INTELLIGENCE - FINAL UPDATE**\n\nVonachen Group is a family-owned commercial cleaning and facility maintenance company established in 1968, now in its fourth generation of leadership. Based in Peoria, Illinois, they have grown to become one of the largest privately-owned janitorial service companies in the Midwest and Southern US with 3,000+ employees across hundreds of locations.\n\n**CRITICAL RECENT DEVELOPMENTS:**\n\n**Leadership Change (2 weeks ago)**: Sudden passing of Tony McMillin, Vice President - creates immediate organizational restructuring needs and potential technology/systems gaps.\n\n**Technology Partnership (1 week ago)**: Productive meeting with WorkWave \"Early Adopters Team\" at Peoria headquarters discussing project milestones, timelines, and AI opportunities - major tech investment signal.\n\n**TECHNOLOGY & INNOVATION PROFILE:**\n\n**Current Technology Stack:**\n- Proprietary service delivery dashboards for performance tracking\n- Multi-tier quality inspection and reporting systems\n- KPI tracking and predictive improvement strategies\n- UV fluorescent technology for surface contamination detection\n- 5S Methodology implementation (Survey, Set-in-Order, Safety, Standardize, Sustain)\n- Dynamic risk assessment capabilities\n- Site-specific benchmarking systems\n\n**Technology Investment Opportunities:**\n1. Dashboard enhancement and modernization\n2. Multi-location management across 14 states\n3. Acquisition integration and system standardization\n4. Advanced workforce management for 3,000+ employees\n5. Real-time operations and 24-hour response capability\n6. Predictive analytics for service optimization\n\n**ENHANCED LEADERSHIP TEAM & BUYING COMMITTEE:**\n- **CEO**: Matthew (Matt) Vonachen - Final decision authority, First Building Service Contractor to serve as ISSA President, Central Illinois Business Hall of Fame inductee\n- **COO**: Michael Disparano - Operational decisions\n- **CFO**: Robert Ferlmann - Financial approval authority\n- **VP Operations**: Dustin Chamberlin - Implementation oversight\n- **Director of IT**: Jeff Durand - Key technology decision maker\n- **Senior Director Business Development**: Sean Litvak, CBSE (Louisville area) - Key contact for new opportunities\n- **Next Generation**: Max Vonachen (industry events), Megan Vonachen (hiring/operations)\n\n**SERVICES & GEOGRAPHIC EXPANSION:**\n\n**Service Lines:**\n- Commercial cleaning with flexible building utilization solutions\n- Healthcare facility cleaning with infection prevention focus\n- Industrial cleaning with machine maintenance and material handling\n- Proprietary Consolidated Service Program (CSP) for healthcare\n- Waste stream management and pallet services\n- Stone/concrete restoration\n\n**Geographic Footprint (14 states):**\nAlabama, Illinois, Indiana, Iowa, Kentucky, Michigan, Mississippi, Missouri, Nebraska, North Carolina, Pennsylvania, Ohio, Tennessee, Wisconsin\n\n**Confirmed Office Locations:**\n- HQ: Peoria, IL (8900 N. Pioneer Road)\n- Rockford, IL | Davenport, IA | Lexington, KY | Louisville, KY | Owensboro, KY | Evansville, IN | Monona, WI | Wausau, WI | Stevens Point, WI\n\n**RECENT ACQUISITIONS & GROWTH:**\n- August 2024: Hasgoe commercial cleaning division (Evansville, IN)\n- Recent: Complete Building Services (CBS) in Clinton, IA\n- Previous: Clearwater Janitorial (Eau Claire, WI)\n- Actively pursuing growth with Pursant LLC as exclusive M&A advisor\n\n**COMPETITIVE ADVANTAGES:**\n- Above-industry staffing levels with \"Vonachen University\" training\n- 24-hour response capability\n- Green Building Certified with honors since 2010 (CIMS Standard)\n- Three-tier quality assurance system\n- Proprietary billing models and value-based services\n- Fifth-largest employer in Greater Peoria Area\n\n**IMMEDIATE OUTREACH OPPORTUNITIES:**\n\n**High-Priority Timing Signals:**\n1. Leadership transition creating operational needs\n2. Active AI/technology evaluation with WorkWave\n3. Recent acquisitions requiring system integration\n4. 14-state operations requiring scalable solutions\n5. Proprietary dashboard systems needing enhancement\n\n**Best Contact Strategy:**\n1. Primary: Jeff Durand (IT Director) - technology solutions\n2. Secondary: Sean Litvak (Sr. Director Business Development) - operational efficiency\n3. Strategic: Matt Vonachen (CEO) - high-level partnership discussions\n\n**Messaging Angles:**\n- AI/Technology Modernization (align with WorkWave initiatives)\n- Multi-state operations management and coordination\n- Acquisition integration and system standardization\n- Leadership transition technology support\n- Dashboard enhancement and predictive analytics\n- Workforce management across 3,000+ employees\n\n**Pain Points & Technology Gaps:**\n- Managing operations across 14 states and hundreds of locations\n- Integrating acquired companies and standardizing systems\n- Real-time service delivery modifications for production workflows\n- Quality assurance scaling across multiple locations\n- Data integration from multiple proprietary systems\n- Enhanced client communication and reporting capabilities",
      "Contacts": [
        "recm0E5x7gKflUxCS",
        "recJgBUTzqUWW9WKS",
        "rec2VLfTiY4vCmb6G",
        "recg8OL2DJ4tE05YU",
        "reczyAFlz857yzDIH",
        "reclbA40HfdJuhAdg",
        "rec1bA3mjPnDWSJoC",
        "reccjEx9SdDbhEFBD",
        "recUfh8Tyuursgyc8",
        "recYBjNn0symeaaTJ",
        "recqFvI7yr3by7TpA",
        "recGJpoZq4tUHqYgr",
        "recV5Ex6iDq6hSjYK",
        "recg9GTCK02ciGuHu",
        "recxbDpKfNC0Vybi8",
        "recdaijJWYifH3Bca",
        "receGjaRkcWCKEbsU",
        "recXM11U4NFk4ppTG",
        "recBJ04en1Vj5rkIT",
        "reckyf7AZ6RcxiSKK",
        "rec42lUq299cBqknQ",
        "reczr7QefeJOjjoRc",
        "rec1G3nHDi5Mpfgax",
        "recbg4mQYxZq4wlV1"
      ],
      "Total Contacts": 24,
      "Industry Insights": {
        "state": "empty",
        "value": null,
        "isStale": true
      },
      "Research": [
        "recH2tqlMU6Cg6X6A",
        "recdeBMZzJRPfI82c",
        "rectj9XQHs08KmCyr",
        "recJIsELGvaVi19Lv",
        "recV1CliEWbt6tGAW",
        "recFCjwD2UWI9Sgy5",
        "rec56KtKMvAzKBwWH",
        "recSr2YKhCC0s3dgP",
        "recyIRDD80QyDtXmq",
        "reccXQErkg3sRdcUY"
      ]
    },
    "createdTime": "2025-07-28T14:19:48.000Z"
  },
  {
    "id": "recJD3CC8Uj98J46m",
    "fields": {
      "Name": "NHMB",
      "Domain": "https://www.nhmutual.com",
      "Industry": "Financial Services - Banking",
      "Current News": "New Hampshire Mutual Bancorp (NHMB) is a bank holding company established in 2013, operating as a shared services organization for three premier mutual savings banks and a trust company. Recent developments include new Board leadership appointments in April 2025 with Joseph Coneeny as Chair and Michelle McEwen as Vice Chair. The company reported strong Q4 2024 financial results with $3.71B in total assets, $15M net income, and recognition among top-performing banks by American Banker. Key executives include CEO Gregg Tewksbury, COO Angela Strozewski, and CIO Robert Soloway. The company operates four subsidiaries: Meredith Village Savings Bank, Merrimack County Savings Bank, Savings Bank of Walpole, and NHTrust Financial Advisors. NHMB emphasizes community banking values and operational efficiency through their shared services model. Technology focus areas include digital transformation, cybersecurity, and regulatory compliance. The company participates in the 'Mutuals Matter' campaign highlighting community-first banking principles. LinkedIn data shows 443 employees, 1,120 followers, and recent activity including promotions in digital banking, new hires in operations, and active recruitment for compliance roles. Key LinkedIn contacts include Robert Clifford (VP Data & BI), Joanne Pearce (Chief Digital Officer), Michael Manley (Data Architecture), and Cheryl Giannasca (SVP HR). Historical analysis reveals strategic formation in 2013 driven by regulatory compliance costs, technology investment needs, and operational efficiency goals. The company has shown consistent growth from $1.46B assets in 2014 to $3.71B in 2024, with strong community involvement (15,000+ volunteer hours annually) and recognition as Business NH Magazine's 2015 Financial Services Business of the Year. Contact information includes main phone 603.225.2793, talent email talent@nhmutual.com, and active LinkedIn presence across all subsidiaries. Potential buying signals include technology modernization initiatives, regulatory compliance needs, risk management solutions, operational efficiency improvements, and data analytics capabilities. Key decision makers span C-suite executives and bank presidents across their subsidiary network, with strong emphasis on community banking values and long-term sustainable growth philosophy.",
      "Contacts": [
        "rec2E8gHCWnGKBjNI",
        "recpQrH5giTk48kqf",
        "recc4yDBvOHbuGwNB",
        "recLdm9oUTFwurvok",
        "recryPAea9erQFkdE",
        "recR233j2kRIxDpGa",
        "recXtg9hNspTOg64h",
        "reckwnduAqISvn0DF",
        "recGmSuWda8418psA",
        "recOj1GF6gyG6QXJ9",
        "reco7EDaHkzlZiFA6",
        "recXRCCexoJ6yM9o8"
      ],
      "Total Contacts": 12,
      "Industry Insights": {
        "state": "empty",
        "value": null,
        "isStale": true
      },
      "Research": [
        "recy2kOA9LIJRubWT",
        "recU1K9EBsl13Wd9v",
        "recOZiPIchK4d8tw8",
        "rec40ZhNxjcjwqQq9",
        "reccrhJ7n6t49muZk",
        "recwVg6bBo0oF2Iam",
        "recO4WI0lgR4Ao14F"
      ]
    },
    "createdTime": "2025-07-28T14:41:09.000Z"
  }
]